BasicGraph/GraphModelLib_v6_Simplified.py
BasicGraph/GraphModelLib_v6_Simplified_LSTMTransform.py
BasicGraph/GraphModelLib_v6_Simplified_LSTMTransform_Oneshot.py
BasicGraph/GraphModelLib_v6_Simplified_LSTMTransform_v0.1.2.py
BasicGraph/GraphModelLib_v6_Simplified_Oneshot.py
BasicGraph/GraphModelLib_v6_Simplified_v0.1.2.py
BasicGraph/__init__.py
SpatialTemporalGraph/GraphModelLib_v5_SpatialTemporal.py
SpatialTemporalGraph/GraphModelLib_v5_SpatialTemporal_v0.1.2.py
SpatialTemporalGraph/__init__.py
TemporalSpatialGraph/GraphModelLib_v6_TemporalSpatial.py
TemporalSpatialGraph/GraphModelLib_v6_TemporalSpatial_Large.py
TemporalSpatialGraph/GraphModelLib_v6_TemporalSpatial_Large_v0.1.2.py
TemporalSpatialGraph/GraphModelLib_v6_TemporalSpatial_v0.1.2.py
TemporalSpatialGraph/__init__.py
graphstam/__init__.py
graphstam/graphstam.py
graphstam/graphstam_bkp.py
hierarchical/BasicGraph/GraphModelLib_Simplified_LSTMTransform_Optimized.py
hierarchical/BasicGraph/GraphModelLib_Simplified_LSTMTransform_Optimized_gscale.py
hierarchical/BasicGraph/GraphModelLib_Simplified_LSTMTransform_Optimized_localscale.py
hierarchical/BasicGraph/GraphModelLib_Simplified_Optimized.py
hierarchical/BasicGraph/__init__.py
hierarchical/graphstam/__init__.py
hierarchical/graphstam/graphstam.py
optimized/BasicGraph/GraphModelLib_Simplified_LSTMTransform_Optimized.py
optimized/BasicGraph/GraphModelLib_Simplified_Optimized.py
optimized/BasicGraph/__init__.py
optimized/SpatialTemporalGraph/GraphModelLib_SpatialTemporal_Optimized.py
optimized/SpatialTemporalGraph/__init__.py
optimized/TemporalSpatialGraph/GraphModelLib_TemporalSpatial_Large_Optimized.py
optimized/TemporalSpatialGraph/GraphModelLib_TemporalSpatial_Optimized.py
optimized/TemporalSpatialGraph/__init__.py
optimized/graphstam/__init__.py
optimized/graphstam/graphstam.py
probabilistic/BasicGraph/GraphModelLib_Simplified_LGSSM.py
probabilistic/BasicGraph/GraphModelLib_Simplified_LSTMTransform_LGSSM.py
probabilistic/BasicGraph/__init__.py
GraphSTAM-1.2.10.dist-info/METADATA
GraphSTAM-1.2.10.dist-info/WHEEL
GraphSTAM-1.2.10.dist-info/top_level.txt
GraphSTAM-1.2.10.dist-info/RECORD
