Metadata-Version: 2.1
Name: GraphSTAM
Version: 1.2.10
Summary: Graph Based Spatio-Temporal Attention Models For Demand Forecasting
Author: Rahul Sinha
Author-email: rahul.sinha@unilever.com
Requires-Dist: statsmodels
Requires-Dist: scipy
Requires-Dist: tweedie
